LICENSE
MANIFEST.in
Makefile
README.md
requirements.txt
setup.cfg
setup.py
src/__init__.py
src/renderer.py
tests/test_renderer.py
userdata_cool.egg-info/PKG-INFO
userdata_cool.egg-info/SOURCES.txt
userdata_cool.egg-info/dependency_links.txt
userdata_cool.egg-info/requires.txt
userdata_cool.egg-info/top_level.txt