Metadata-Version: 1.0
Name: userdata-cool
Version: 0.1.2
Summary: Let you write user data easily
Home-page: https://github.com/ycliuhw/userdata-generator
Author: Yang Kelvin Liu
Author-email: ycliuhw@gmail.com
License: Apache License 2.0
Keywords: troposphere,cloudformation,python3,userdata
Platform: UNKNOWN
